group13_lab5_part3/unit2.v
//lab 05 part 03 - Group 13

module twos_compliment(IN,OUT);
    // declaring ports
    input [7:0] IN;
    output [7:0] OUT;

    // 2's complement operation
        //adding artificial delay of 1 second
        // Out = (fipping the bits in IN) + 1
    assign #1 OUT =(~IN)+1;

endmodule

module mux(IN1,IN2,SELECT,OUT);

    //declaring ports
    input [7:0] IN1, IN2;   // 2 inputs
    input SELECT;           // select bit input
    output reg [7:0] OUT;   // output

    // always taking inputs and updating the regarding output accordingly
    always @(IN1,IN2,SELECT)

    begin
        //if select bit is low
        if (SELECT==1'b0)
            begin
                assign OUT = IN1;  //switch to IN1
            end
        // else select bit is high
        else
            begin
                assign OUT = IN2;  //switch to IN2
            end
    end

endmodule


/*

//test twos_compliment
module stimulus;

    reg [7:0] IN;
    wire [7:0] OUT;

    twos_compliment test_tc(IN,OUT);

    initial begin
        IN=8'b00001111;
        #5
        $display("%b",OUT);

    end
endmodule 
*/

group13_lab5_part3/regfile.v
//lab 05 part 03 - Group 13

module regfile(IN,INADDRESS,OUT1ADDRESS,OUT2ADDRESS,CLK,RESET,WRITE,REGOUT1,REGOUT2,INSTRUCTION);

    input [7:0] IN;   // 8-bit input data to be written into the register
    input [2:0] INADDRESS, OUT1ADDRESS, OUT2ADDRESS;   // 3-bit input addresses for IN, OUT1, and OUT2
    input CLK, RESET, WRITE;   // Clock signal, Reset signal, Write enable signal

    output reg [7:0] REGOUT1, REGOUT2; // Output data from registers specified by OUT1ADDRESS and OUT2ADDRESS

    reg [7:0] regArray [0:7];   // 8-element array of 8-bit registers

	input [31:0] INSTRUCTION;

    integer i;  // Loop variable for iterating through the array of registers

    // Reading the OUTADDRESSES and asynchronously loading values to OUT1 and OUT2 with a delay of 2 time units
	always @(INSTRUCTION)
	begin
		 REGOUT1 <= #2 regArray[OUT1ADDRESS];		
		 REGOUT2 <= #2 regArray[OUT2ADDRESS];		
	end

	// Write and Reset (synchronous operations)
	always @ (posedge CLK)
	begin
	    // When RESET is high, clear all values of the registers to zero
		if (RESET)			
		begin
		    #1 for (i = 0; i < 8; i = i + 1)    // Iterate over all 8 register addresses with a delay of 1 time unit
			begin
				regArray[i] <= 8'b00000000;    // Reset all registers to zero
			end
		end


     	// If the WRITE signal is high, store the input data IN into the target register specified by INADDRESS
		else if (WRITE)  
		begin		
			#1
			regArray[INADDRESS] <= IN;    // Write operation with a delay of 1 time unit
			
		end
		
	end
	
endmodule

group13_lab5_part3/alu.v
//lab 05 part 03 - Group 13

module alu(Data1, Data2, Result, Select);
	
	// Input ports
	input [7:0] Data1, Data2;   // 8-bit data inputs
	input [2:0] Select;          // 3-bit selection input for choosing operation
	
	output reg [7:0] Result;     // Output port for the result
	
	wire [7:0] forwardWire, addWire, andWire, orWire;   // Wires for outputs of each functional unit
	
	// Functional units to forward the results of the units to corresponding wire
	FORWARD forwardUnit(Data2, forwardWire);   // Forwarding unit
	ADD addUnit(Data1, Data2, addWire);        // Addition unit
	AND andUnit(Data1, Data2, andWire);        // Bitwise AND unit
	OR orUnit(Data1, Data2, orWire);           // Bitwise OR unit
	
	
	// RESULT output must be updated whenever any of the inputs or functional outputs changes
	always @ (Data1,Data2,Select) 
	begin
		// Select the operation based on the value of Select input
		case (Select)		
			3'b000 :	Result = forwardWire;   // SELECT = 0 : FORWARD operation
			3'b001 :	Result = addWire;       // SELECT = 1 : ADD operation
			3'b010 :	Result = andWire;       // SELECT = 2 : AND operation
			3'b011 :	Result = orWire;        // SELECT = 3 : OR operation
		endcase
	end
		
endmodule


// Forwarding unit
module FORWARD(Data2, Result);

	input [7:0] Data2;     // Input port for forwarding
	output [7:0] Result;   // Output port for forwarding

	// Assigns value of Data2 to the Result for forwarding after 1 time delay
	assign #1 Result = Data2;

endmodule

// Addition unit
module ADD(Data1, Data2, Result);

	input [7:0] Data1, Data2;    // 8-bit input ports for addition
	output [7:0] Result;         // Output port for addition
	
	// Assigns addition of Data1 and Data2 to Result after 2 time unit delay
	assign #2 Result = Data1 + Data2;

endmodule

// Bitwise AND unit
module AND(Data1, Data2, Result);

	input [7:0] Data1, Data2;    // 8-bit input ports for AND operation
	output [7:0] Result;         // Output port for AND operation
	
	// Assigns logical AND result of Data1 and Data2 to Result after 1 time unit delay
	assign #1 Result = Data1 & Data2;

endmodule

// Bitwise OR unit
module OR(Data1, Data2, Result);

	input [7:0] Data1, Data2;    // Input ports for OR operation
	output [7:0] Result;         // Output port for OR operation
	
	// Assigns logical OR result of Data1 and Data2 to Result after 1 time unit delay
	assign #1 Result = Data1 | Data2;

endmodule

group13_lab5_part3/cpu.v
//lab 05 part 03 - Group 13

`include "alu.v"
`include "regfile.v"
`include "unit2.v"

// Register File module to store output values from ALU
module cpu(PC,INSTRUCTION, CLK, RESET) ;

    //input Instruction
    input [31:0] INSTRUCTION;
    // clock signal and reset signal
    input CLK;
    input RESET;
    //Output port - program counter
    output reg [31:0] PC;
    //Current OPCODE for the CPU
    reg [7:0] OPCODE;

    //Declaring Connections to other modules
    //  alu
    wire [7:0] DATA1,DATA2; // input operands to alu
    reg [2:0] ALUOP;       // select input to alu (for selecting operation)
    wire [7:0] ALURESULT;   // output from alu - Result

    // register file
    wire[2:0] WRITEREG;    // input address to register file
    /*                        output ALURESULT from alu as input to register file */
    wire[2:0] READREG1;    // output-1  address from register file
    wire[2:0] READREG2;    // output-2 address from register file
    wire[7:0] REGOUT2;     // output-2 from reg file
    /*                        output-1 from reg file REGOUT1[7:0] is DATA1 input to alu*/
    reg WRITEENABLE;       // Writeenable to reg file

    // immediate mux
    wire [7:0] IMMEDIATE;   // immediate value as input_1 to the immediate_mux
    wire [7:0] NEGMUXOUT;   // negation_mux output as input_2 to the immediate_mux
    /*OUTPUT                   output of the immediate mux is DATA2 input to the ALU */
    reg IMSELECT;           // Select bit input to the immediate_mux

    // negation mux
    wire [7:0] TWOSOUT  ;   // Output from the 2's compliment as input_1 to the negation_mux
    /*INPUT2                   REGOUT2[7:0] Output from the reg file as input_2 to the negation_mux */
    /*OUTPUT                   NEGMUXOUT[7:0] as the output from negation_mux */
    reg NEGSELECT;           // Select bit input to the negation mux

    // program counter
    reg [31:0] PCADDED;            // output from program_counter 


    //calling all the cpu modules
    //alu
    alu cpu_alu(DATA1,DATA2,ALURESULT,ALUOP);

    //register file
    regfile cpu_reg_file(ALURESULT,WRITEREG,READREG1,READREG2,CLK,RESET,WRITEENABLE,DATA1,REGOUT2,INSTRUCTION);

    // 2's compliment
    twos_compliment cpu_tc(REGOUT2,TWOSOUT);

    // Negation mux
    mux cpu_neg_mux(REGOUT2,TWOSOUT,NEGSELECT,NEGMUXOUT);

    // Immediate mux
    mux cpu_im_mux(NEGMUXOUT,IMMEDIATE,IMSELECT,DATA2);
    

    //Control Unit-Program Counter update
    // program counter adder
    always @(PC) begin
    // assign PC_value +1 with 1 s  artificial delay
        #1 PCADDED=PC+4;
    end

    always @(posedge CLK) begin //always at the +ve edge of the clock pulse
      
        // if reset is high program counter value=>0
        if (RESET==1'b1)   begin 
        #1 PC =0;    //+1 time unit delay
        end
    end
    
    always @(posedge CLK) begin   // pc update
        #1 PC =PCADDED;           //+ 1 time unit delay
    end
    

    //assigning fields of instruction format
    /* |   Opcode   |   Rd    |    Rt    |  Rs/Imm  |   */

    assign WRITEREG=INSTRUCTION[23:16];  //Rd => destination register
    assign READREG1=INSTRUCTION[15:8];   //Rt => 1st operand register
    assign READREG2=INSTRUCTION[7:0];    //Rs => 2nd operand register
    assign IMMEDIATE=INSTRUCTION[7:0];   //immediate value register

    //Instruction Decoding

    always @(INSTRUCTION)   //decoding process occurs continuosly
    begin
        OPCODE=INSTRUCTION[31:24];       //Opcode field in the instruction format
        #1                              //adding 1 time unit delay

        case(OPCODE)
            //loadi 
            8'b00000000:	begin
                                ALUOP = 3'b000;			//Set alu to FORWARD
                                IMSELECT = 1'b1;		//Set immeiate_mux to select immediate value
                                NEGSELECT = 1'b0;		//Set neg_mux to select positive sign
                                WRITEENABLE = 1'b1;		//Enable writing to register
                            end
            
            //mov
			8'b00000001:	begin
								ALUOP = 3'b000;			//Set alu to FORWARD
								IMSELECT = 1'b0;		//Set imm_mux to select register i/p
								NEGSELECT = 1'b0;		//Set neg_mux to select positive sign
								WRITEENABLE = 1'b1;		//Enable writing to register
							end
            
            //add
			8'b00000010:	begin
								ALUOP = 3'b001;			//Set alu to ADD
								IMSELECT= 1'b0;		    //Set imm_mux to select register i/p
								NEGSELECT = 1'b0;		//Set neg_mux to select positive sign
								WRITEENABLE = 1'b1;		//Enable writing to register
							end	
		
			//sub 
			8'b00000011:	begin
								ALUOP = 3'b001;			//Set alu to ADD
								IMSELECT = 1'b0;		//Set imm_mux to select register input
								NEGSELECT = 1'b1;		//Set neg_mux to select negative sign
								WRITEENABLE = 1'b1;		//Enable writing to register
							end

			//and 
			8'b00000100:	begin
								ALUOP = 3'b010;			//Set alu to AND
								IMSELECT = 1'b0;		//Set imm_mux to select register input
								NEGSELECT = 1'b0;		//Set neg_mux to select positive sign
								WRITEENABLE = 1'b1;		//Enable writing to register
							end
							
			//or 
			8'b00000101:	begin
								ALUOP = 3'b011;			//Set ALU to OR
								IMSELECT = 1'b0;		//Set imm_mux to select register input
								NEGSELECT = 1'b0;		//Set neg_mux to select positive sign
								WRITEENABLE = 1'b1;		//Enable writing to register
							end
			
        endcase
    end

   
endmodule

group13_lab5_part3/cpu_tb.v
//lab 05 part 03 - Group 13

`include "cpu.v"

module cpu_tb;

    reg CLK, RESET;
    wire [31:0] PC;
    wire [31:0] INSTRUCTION;
    
    /* 
    ------------------------
     SIMPLE INSTRUCTION MEM
    ------------------------
    */
    
    // TODO: Initialize an array of registers (8x1024) named 'instr_mem' to be used as instruction memory
	reg[7:0] instr_mem[0:1023];
	
    
    // TODO: Create combinational logic to support CPU instruction fetching, given the Program Counter(PC) value 
    //       (make sure you include the delay for instruction fetching here)
	assign #2 INSTRUCTION = {instr_mem[PC+3], instr_mem[PC+2], instr_mem[PC+1], instr_mem[PC]};
    
    initial
    begin
        // Initialize instruction memory with the set of instructions you need execute on CPU
        
        // METHOD 1: manually loading instructions to instr_mem
        //{instr_mem[10'd3], instr_mem[10'd2], instr_mem[10'd1], instr_mem[10'd0]} = 32'b00000000000001000000000000000101;
        //{instr_mem[10'd7], instr_mem[10'd6], instr_mem[10'd5], instr_mem[10'd4]} = 32'b00000000000000100000000000001001;
        //{instr_mem[10'd11], instr_mem[10'd10], instr_mem[10'd9], instr_mem[10'd8]} = 32'b00000010000001100000010000000010;
        
        // METHOD 2: loading instr_mem content from instr_mem.mem file
        $readmemb("instr_mem.mem", instr_mem);
    end
    
    /* 
    -----
     CPU
    -----
    */
    cpu mycpu(PC, INSTRUCTION, CLK, RESET);

    initial
    begin
    
        // generate files needed to plot the waveform using GTKWave
        $dumpfile("cpu_wavedata.vcd");
		$dumpvars(0, cpu_tb);
        
        CLK = 1'b0;
        RESET = 1'b1;
        
        // TODO: Reset the CPU (by giving a pulse to RESET signal) to start the program execution
		#5
		RESET = 1'b0;
        
        // finish simulation after some time
        #300
        $finish;
        
    end
    
    // clock signal generation
    always
        #4 CLK = ~CLK;
        

endmodule

group13_lab5_part3/cpu_wavedata.vcd
$date
	Tue May 28 18:47:20 2024
$end
$version
	Icarus Verilog
$end
$timescale
	1s
$end
$scope module cpu_tb $end
$var wire 32 ! PC [31:0] $end
$var wire 32 " INSTRUCTION [31:0] $end
$var reg 1 # CLK $end
$var reg 1 $ RESET $end
$scope module mycpu $end
$var wire 1 # CLK $end
$var wire 32 % INSTRUCTION [31:0] $end
$var wire 1 $ RESET $end
$var wire 3 & WRITEREG [2:0] $end
$var wire 8 ' TWOSOUT [7:0] $end
$var wire 8 ( REGOUT2 [7:0] $end
$var wire 3 ) READREG2 [2:0] $end
$var wire 3 * READREG1 [2:0] $end
$var wire 8 + NEGMUXOUT [7:0] $end
$var wire 8 , IMMEDIATE [7:0] $end
$var wire 8 - DATA2 [7:0] $end
$var wire 8 . DATA1 [7:0] $end
$var wire 8 / ALURESULT [7:0] $end
$var reg 3 0 ALUOP [2:0] $end
$var reg 1 1 IMSELECT $end
$var reg 1 2 NEGSELECT $end
$var reg 8 3 OPCODE [7:0] $end
$var reg 32 4 PC [31:0] $end
$var reg 32 5 PCADDED [31:0] $end
$var reg 1 6 WRITEENABLE $end
$scope module cpu_alu $end
$var wire 3 7 Select [2:0] $end
$var wire 8 8 orWire [7:0] $end
$var wire 8 9 forwardWire [7:0] $end
$var wire 8 : andWire [7:0] $end
$var wire 8 ; addWire [7:0] $end
$var wire 8 < Data2 [7:0] $end
$var wire 8 = Data1 [7:0] $end
$var reg 8 > Result [7:0] $end
$scope module addUnit $end
$var wire 8 ? Result [7:0] $end
$var wire 8 @ Data2 [7:0] $end
$var wire 8 A Data1 [7:0] $end
$upscope $end
$scope module andUnit $end
$var wire 8 B Result [7:0] $end
$var wire 8 C Data2 [7:0] $end
$var wire 8 D Data1 [7:0] $end
$upscope $end
$scope module forwardUnit $end
$var wire 8 E Result [7:0] $end
$var wire 8 F Data2 [7:0] $end
$upscope $end
$scope module orUnit $end
$var wire 8 G Result [7:0] $end
$var wire 8 H Data2 [7:0] $end
$var wire 8 I Data1 [7:0] $end
$upscope $end
$upscope $end
$scope module cpu_im_mux $end
$var wire 8 J IN2 [7:0] $end
$var wire 1 1 SELECT $end
$var wire 8 K IN1 [7:0] $end
$var reg 8 L OUT [7:0] $end
$upscope $end
$scope module cpu_neg_mux $end
$var wire 1 2 SELECT $end
$var wire 8 M IN2 [7:0] $end
$var wire 8 N IN1 [7:0] $end
$var reg 8 O OUT [7:0] $end
$upscope $end
$scope module cpu_reg_file $end
$var wire 1 # CLK $end
$var wire 8 P IN [7:0] $end
$var wire 3 Q INADDRESS [2:0] $end
$var wire 32 R INSTRUCTION [31:0] $end
$var wire 3 S OUT1ADDRESS [2:0] $end
$var wire 3 T OUT2ADDRESS [2:0] $end
$var wire 1 $ RESET $end
$var wire 1 6 WRITE $end
$var reg 8 U REGOUT1 [7:0] $end
$var reg 8 V REGOUT2 [7:0] $end
$var integer 32 W i [31:0] $end
$upscope $end
$scope module cpu_tc $end
$var wire 8 X IN [7:0] $end
$var wire 8 Y OUT [7:0] $end
$upscope $end
$upscope $end
$upscope $end
$enddefinitions $end
#0
$dumpvars
bx Y
bx X
bx W
bx V
bx U
bx T
bx S
bx R
bx Q
bx P
bx O
bx N
bx M
bx L
bx K
bx J
bx I
bx H
bx G
bx F
bx E
bx D
bx C
bx B
bx A
bx @
bx ?
bx >
bx =
bx <
bx ;
bx :
bx 9
bx 8
bx 7
x6
bx 5
bx 4
bx 3
x2
x1
bx 0
bx /
bx .
bx -
bx ,
bx +
bx *
bx )
bx (
bx '
bx &
bx %
1$
0#
bx "
bx !
$end
#4
1#
#5
b1000 W
b0 !
b0 4
0$
#6
b100 5
#7
b0 &
b0 Q
b0 *
b0 S
b101 )
b101 T
b101 -
b101 <
b101 @
b101 C
b101 F
b101 H
b101 L
b101 ,
b101 J
b0 3
b101 "
b101 %
b101 R
#8
b101 /
b101 >
b101 P
bx1x1 8
bx1x1 G
b0x0x :
b0x0x B
b101 9
b101 E
16
02
11
b0 0
b0 7
0#
#12
1#
#13
b100 !
b100 4
#14
b1000 5
#15
b1 &
b1 Q
b1 )
b1 T
b1001 -
b1001 <
b1001 @
b1001 C
b1001 F
b1001 H
b1001 L
b1001 ,
b1001 J
b10000000000001001 "
b10000000000001001 %
b10000000000001001 R
#16
bx1xx1 8
bx1xx1 G
b0x00x :
b0x00x B
b1001 9
b1001 E
0#
#17
b1001 /
b1001 >
b1001 P
b0 +
b0 K
b0 O
b0 (
b0 N
b0 V
b0 X
b101 .
b101 =
b101 A
b101 D
b101 I
b101 U
#18
b0 '
b0 M
b0 Y
b1101 8
b1101 G
b1 :
b1 B
#19
b1110 ;
b1110 ?
#20
1#
#21
b1000 !
b1000 4
#22
b1100 5
#23
b10 &
b10 Q
b1 -
b1 <
b1 @
b1 C
b1 F
b1 H
b1 L
b1 ,
b1 J
b1 3
b1000000100000000000000001 "
b1000000100000000000000001 %
b1000000100000000000000001 R
#24
b1 /
b1 >
b1 P
b0 -
b0 <
b0 @
b0 C
b0 F
b0 H
b0 L
b101 8
b101 G
b1 9
b1 E
01
0#
#25
b0 /
b0 >
b0 P
b1001 -
b1001 <
b1001 @
b1001 C
b1001 F
b1001 H
b1001 L
b1001 +
b1001 K
b1001 O
b1001 (
b1001 N
b1001 V
b1001 X
b0 :
b0 B
b0 9
b0 E
#26
b11110111 '
b11110111 M
b11110111 Y
b1101 8
b1101 G
b1 :
b1 B
b1001 9
b1001 E
#28
1#
#29
b1100 !
b1100 4
#30
b10000 5
#31
b11 &
b11 Q
b10 *
b10 S
b0 )
b0 T
b0 ,
b0 J
b10 3
b10000000110000001000000000 "
b10000000110000001000000000 %
b10000000110000001000000000 R
#32
b1110 /
b1110 >
b1110 P
b1 0
b1 7
0#
#36
1#
#37
b10000 !
b10000 4
#38
b10100 5
#39
b100 &
b100 Q
b11 *
b11 S
b1 )
b1 T
b1 ,
b1 J
b11 3
b11000001000000001100000001 "
b11000001000000001100000001 %
b11000001000000001100000001 R
#40
b11110111 -
b11110111 <
b11110111 @
b11110111 C
b11110111 F
b11110111 H
b11110111 L
b11110111 +
b11110111 K
b11110111 O
12
0#
#41
b101 (
b101 N
b101 V
b101 X
b0 .
b0 =
b0 A
b0 D
b0 I
b0 U
b11110111 8
b11110111 G
b101 :
b101 B
b11110111 9
b11110111 E
#42
b11111011 -
b11111011 <
b11111011 @
b11111011 C
b11111011 F
b11111011 H
b11111011 L
b11111011 +
b11111011 K
b11111011 O
b11111011 '
b11111011 M
b11111011 Y
b0 :
b0 B
#43
b11111011 8
b11111011 G
b11111011 9
b11111011 E
#44
b11111011 ;
b11111011 ?
1#
#45
b10100 !
b10100 4
#46
b11000 5
#47
b0 &
b0 Q
b0 *
b0 S
b101 )
b101 T
b1110101 ,
b1110101 J
b0 3
b1110101 "
b1110101 %
b1110101 R
#48
b101 +
b101 K
b101 O
b1110101 -
b1110101 <
b1110101 @
b1110101 C
b1110101 F
b1110101 H
b1110101 L
b11111011 /
b11111011 >
b11111011 P
02
11
b0 0
b0 7
0#
#49
b1110101 /
b1110101 >
b1110101 P
b1001 +
b1001 K
b1001 O
b1001 (
b1001 N
b1001 V
b1001 X
b1110 .
b1110 =
b1110 A
b1110 D
b1110 I
b1110 U
b1110101 8
b1110101 G
b1110101 9
b1110101 E
#50
b11110111 '
b11110111 M
b11110111 Y
b1111111 8
b1111111 G
b100 :
b100 B
#51
b10000011 ;
b10000011 ?
#52
1#
#53
b11000 !
b11000 4
#54
b11100 5
#55
b1 &
b1 Q
b10 )
b10 T
b10010010 -
b10010010 <
b10010010 @
b10010010 C
b10010010 F
b10010010 H
b10010010 L
b10010010 ,
b10010010 J
b10000000010010010 "
b10000000010010010 %
b10000000010010010 R
#56
b10011110 8
b10011110 G
b10 :
b10 B
b10010010 9
b10010010 E
0#
#57
b10010010 /
b10010010 >
b10010010 P
b0 +
b0 K
b0 O
b0 (
b0 N
b0 V
b0 X
b1110101 .
b1110101 =
b1110101 A
b1110101 D
b1110101 I
b1110101 U
b10100000 ;
b10100000 ?
#58
b0 '
b0 M
b0 Y
b11110111 8
b11110111 G
b10000 :
b10000 B
#59
b111 ;
b111 ?
#60
1#
#61
b11100 !
b11100 4
#62
b100000 5
#63
b101 &
b101 Q
b1 *
b1 S
b0 )
b0 T
b0 -
b0 <
b0 @
b0 C
b0 F
b0 H
b0 L
b0 ,
b0 J
b100 3
b100000001010000000100000000 "
b100000001010000000100000000 %
b100000001010000000100000000 R
#64
b0 /
b0 >
b0 P
b1110101 8
b1110101 G
b0 :
b0 B
b0 9
b0 E
01
b10 0
b10 7
0#
#65
b1110101 ;
b1110101 ?
#68
1#
#69
b100000 !
b100000 4
#70
b100100 5
#71
b110 &
b110 Q
b101 *
b101 S
b10 )
b10 T
b10 ,
b10 J
b101 3
b101000001100000010100000010 "
b101000001100000010100000010 %
b101000001100000010100000010 R
#72
b1110101 /
b1110101 >
b1110101 P
b11 0
b11 7
0#
#73
b1110101 -
b1110101 <
b1110101 @
b1110101 C
b1110101 F
b1110101 H
b1110101 L
b1110101 +
b1110101 K
b1110101 O
b1110101 (
b1110101 N
b1110101 V
b1110101 X
b10010010 .
b10010010 =
b10010010 A
b10010010 D
b10010010 I
b10010010 U
#74
b10001011 '
b10001011 M
b10001011 Y
b11110111 8
b11110111 G
b10000 :
b10000 B
b1110101 9
b1110101 E
#75
b111 ;
b111 ?
#76
1#
#77
b100100 !
b100100 4
#78
b101000 5
#79
bx &
bx Q
bx *
bx S
bx )
bx T
bx ,
bx J
bx 3
bx "
bx %
bx R
#80
0#
#81
b11110111 /
b11110111 >
b11110111 P
b0 -
b0 <
b0 @
b0 C
b0 F
b0 H
b0 L
b0 +
b0 K
b0 O
b0 (
b0 N
b0 V
b0 X
b0 .
b0 =
b0 A
b0 D
b0 I
b0 U
#82
b0 '
b0 M
b0 Y
b0 8
b0 G
b0 :
b0 B
b0 9
b0 E
#83
b0 ;
b0 ?
#84
1#
#85
b101000 !
b101000 4
#86
b101100 5
#88
0#
#92
1#
#93
b101100 !
b101100 4
#94
b110000 5
#96
0#
#100
1#
#101
b110000 !
b110000 4
#102
b110100 5
#104
0#
#108
1#
#109
b110100 !
b110100 4
#110
b111000 5
#112
0#
#116
1#
#117
b111000 !
b111000 4
#118
b111100 5
#120
0#
#124
1#
#125
b111100 !
b111100 4
#126
b1000000 5
#128
0#
#132
1#
#133
b1000000 !
b1000000 4
#134
b1000100 5
#136
0#
#140
1#
#141
b1000100 !
b1000100 4
#142
b1001000 5
#144
0#
#148
1#
#149
b1001000 !
b1001000 4
#150
b1001100 5
#152
0#
#156
1#
#157
b1001100 !
b1001100 4
#158
b1010000 5
#160
0#
#164
1#
#165
b1010000 !
b1010000 4
#166
b1010100 5
#168
0#
#172
1#
#173
b1010100 !
b1010100 4
#174
b1011000 5
#176
0#
#180
1#
#181
b1011000 !
b1011000 4
#182
b1011100 5
#184
0#
#188
1#
#189
b1011100 !
b1011100 4
#190
b1100000 5
#192
0#
#196
1#
#197
b1100000 !
b1100000 4
#198
b1100100 5
#200
0#
#204
1#
#205
b1100100 !
b1100100 4
#206
b1101000 5
#208
0#
#212
1#
#213
b1101000 !
b1101000 4
#214
b1101100 5
#216
0#
#220
1#
#221
b1101100 !
b1101100 4
#222
b1110000 5
#224
0#
#228
1#
#229
b1110000 !
b1110000 4
#230
b1110100 5
#232
0#
#236
1#
#237
b1110100 !
b1110100 4
#238
b1111000 5
#240
0#
#244
1#
#245
b1111000 !
b1111000 4
#246
b1111100 5
#248
0#
#252
1#
#253
b1111100 !
b1111100 4
#254
b10000000 5
#256
0#
#260
1#
#261
b10000000 !
b10000000 4
#262
b10000100 5
#264
0#
#268
1#
#269
b10000100 !
b10000100 4
#270
b10001000 5
#272
0#
#276
1#
#277
b10001000 !
b10001000 4
#278
b10001100 5
#280
0#
#284
1#
#285
b10001100 !
b10001100 4
#286
b10010000 5
#288
0#
#292
1#
#293
b10010000 !
b10010000 4
#294
b10010100 5
#296
0#
#300
1#
#301
b10010100 !
b10010100 4
#302
b10011000 5
