group13_lab5_part1/alu.v
//Lab 05 - part 01 (ALU)
//Group 13 

module alu(Data1, Data2, Result, Select);
	
	// Input ports
	input [7:0] Data1, Data2;   // 8-bit data inputs
	input [2:0] Select;          // 3-bit selection input for choosing operation
	
	output reg [7:0] Result;     // Output port for the result
	
	wire [7:0] forwardWire, addWire, andWire, orWire;   // Wires for outputs of each functional unit
	
	// Functional units to forward the results of the units to corresponding wire
	FORWARD forwardUnit(Data2, forwardWire);   // Forwarding unit
	ADD addUnit(Data1, Data2, addWire);        // Addition unit
	AND andUnit(Data1, Data2, andWire);        // Bitwise AND unit
	OR orUnit(Data1, Data2, orWire);           // Bitwise OR unit
	
	
	// RESULT output must be updated whenever any of the inputs or functional outputs changes
	always @ (*) 
	begin
		// Select the operation based on the value of Select input
		case (Select)		
			3'b000 :	Result = forwardWire;   // SELECT = 0 : FORWARD operation
			3'b001 :	Result = addWire;       // SELECT = 1 : ADD operation
			3'b010 :	Result = andWire;       // SELECT = 2 : AND operation
			3'b011 :	Result = orWire;        // SELECT = 3 : OR operation
		endcase
	end
		
endmodule


// Forwarding unit
module FORWARD(Data2, Result);

	input [7:0] Data2;     // Input port for forwarding
	output [7:0] Result;   // Output port for forwarding

	// Assigns value of Data2 to the Result for forwarding after 1 time delay
	assign #1 Result = Data2;

endmodule

// Addition unit
module ADD(Data1, Data2, Result);

	input [7:0] Data1, Data2;    // 8-bit input ports for addition
	output [7:0] Result;         // Output port for addition
	
	// Assigns addition of Data1 and Data2 to Result after 2 time unit delay
	assign #2 Result = Data1 + Data2;

endmodule

// Bitwise AND unit
module AND(Data1, Data2, Result);

	input [7:0] Data1, Data2;    // 8-bit input ports for AND operation
	output [7:0] Result;         // Output port for AND operation
	
	// Assigns logical AND result of Data1 and Data2 to Result after 1 time unit delay
	assign #1 Result = Data1 & Data2;

endmodule

// Bitwise OR unit
module OR(Data1, Data2, Result);

	input [7:0] Data1, Data2;    // Input ports for OR operation
	output [7:0] Result;         // Output port for OR operation
	
	// Assigns logical OR result of Data1 and Data2 to Result after 1 time unit delay
	assign #1 Result = Data1 | Data2;

endmodule

group13_lab5_part1/alu_tb.v
//group 13

`include "alu.v"   // Include the ALU module

module alu_tb;

	// Input ports 
	reg [7:0] op1, op2;   // 8-bit operands
	reg [2:0] sel;         // 3-bit selection signal for choosing operation

	wire [7:0] result;    // Output port for the result

	alu alu_test(op1, op2, result, sel);   // Instantiate the ALU module

    // Initial block to monitor changes and dump wavedata to a VCD file
	initial begin
		$dumpfile("alu_wv.vcd");   // Set the name of the VCD file
		$dumpvars(0, alu_test);     // Dump the variables in the ALU module
		$monitor("TIME = %g OP1 = %d OP2 = %d SEL = %b RESULT = %d", $time, op1, op2, sel, result);   // Monitor changes and display relevant information
	end
	
	initial begin
		// Forwarding operation
		op1 = 8'b00000101;   // Set operand 1
		op2 = 8'b00000111;   // Set operand 2
		sel = 3'b000;        // Set selection signal for forwarding operation
		
		#5   // Wait for 5 time units
		
		// Add operation
		op1 = 8'b1010_0000;   // Set operand 1
		op2 = 8'b0000_1010;   // Set operand 2
		sel = 3'b001;         // Set selection signal for addition operation
		
		#10   // Wait for 10 time units
		
		// AND operation 
		op1 = 8'b00010101;   // Set operand 1
		op2 = 8'b00011101;   // Set operand 2
		sel = 3'b010;        // Set selection signal for bitwise AND operation
		
		#15   // Wait for 15 time units
		
		// OR operation
		op1 = 8'b00010101;   // Set operand 1
		op2 = 8'b00100100;   // Set operand 2
		sel = 3'b011;        // Set selection signal for bitwise OR operation
		
	end	

endmodule

group13_lab5_part1/alu_wv.vcd
$date
	Tue May 28 10:26:11 2024
$end
$version
	Icarus Verilog
$end
$timescale
	1s
$end
$scope module alu_tb $end
$scope module alu_test $end
$var wire 8 ! Data1 [7:0] $end
$var wire 8 " Data2 [7:0] $end
$var wire 3 # Select [2:0] $end
$var wire 8 $ orWire [7:0] $end
$var wire 8 % forwardWire [7:0] $end
$var wire 8 & andWire [7:0] $end
$var wire 8 ' addWire [7:0] $end
$var reg 8 ( Result [7:0] $end
$scope module addUnit $end
$var wire 8 ) Data1 [7:0] $end
$var wire 8 * Data2 [7:0] $end
$var wire 8 + Result [7:0] $end
$upscope $end
$scope module andUnit $end
$var wire 8 , Data1 [7:0] $end
$var wire 8 - Data2 [7:0] $end
$var wire 8 . Result [7:0] $end
$upscope $end
$scope module forwardUnit $end
$var wire 8 / Data2 [7:0] $end
$var wire 8 0 Result [7:0] $end
$upscope $end
$scope module orUnit $end
$var wire 8 1 Data1 [7:0] $end
$var wire 8 2 Data2 [7:0] $end
$var wire 8 3 Result [7:0] $end
$upscope $end
$upscope $end
$upscope $end
$enddefinitions $end
#0
$dumpvars
bx 3
b111 2
b101 1
bx 0
b111 /
bx .
b111 -
b101 ,
bx +
b111 *
b101 )
bx (
bx '
bx &
bx %
bx $
b0 #
b111 "
b101 !
$end
#1
b111 (
b111 $
b111 3
b101 &
b101 .
b111 %
b111 0
#2
b1100 '
b1100 +
#5
b1100 (
b1 #
b1010 "
b1010 *
b1010 -
b1010 /
b1010 2
b10100000 !
b10100000 )
b10100000 ,
b10100000 1
#6
b0 &
b0 .
b10101010 $
b10101010 3
b1010 %
b1010 0
#7
b10101010 (
b10101010 '
b10101010 +
#15
b0 (
b10 #
b11101 "
b11101 *
b11101 -
b11101 /
b11101 2
b10101 !
b10101 )
b10101 ,
b10101 1
#16
b10101 (
b10101 &
b10101 .
b11101 $
b11101 3
b11101 %
b11101 0
#17
b110010 '
b110010 +
#30
b11101 (
b11 #
b100100 "
b100100 *
b100100 -
b100100 /
b100100 2
#31
b110101 (
b100 &
b100 .
b110101 $
b110101 3
b100100 %
b100100 0
#32
b111001 '
b111001 +
