group13_lab5_part2/regfile.v
//group 13 - part2 (register file)

module regfile(IN,INADDRESS,OUT1ADDRESS,OUT2ADDRESS,CLK,RESET,WRITE,REGOUT1,REGOUT2);

    input [7:0] IN;   // 8-bit input data to be written into the register
    input [2:0] INADDRESS, OUT1ADDRESS, OUT2ADDRESS;   // 3-bit input addresses for IN, OUT1, and OUT2
    input CLK, RESET, WRITE;   // Clock signal, Reset signal, Write enable signal

    output [7:0] REGOUT1, REGOUT2; // Output data from registers specified by OUT1ADDRESS and OUT2ADDRESS

    reg [7:0] regArray [0:7];   // 8-element array of 8-bit registers

    integer i;  // Loop variable for iterating through the array of registers

    // Reading the OUTADDRESSES and asynchronously loading values to OUT1 and OUT2 with a delay of 2 time units
	assign #2 REGOUT1 = regArray[OUT1ADDRESS];		
	assign #2 REGOUT2 = regArray[OUT2ADDRESS];		
	
	// Write and Reset (synchronous operations)
	always @ (posedge CLK)
	begin
	    // When RESET is high, clear all values of the registers to zero
		if (RESET)			
		begin
		    #1 for (i = 0; i < 8; i = i + 1)    // Iterate over all 8 register addresses with a delay of 1 time unit
			begin
				regArray[i] <= 8'b00000000;    // Reset all registers to zero
			end
		end


     	// If the WRITE signal is high, store the input data IN into the target register specified by INADDRESS
		else if (WRITE)  
		begin		
			#1
			regArray[INADDRESS] <= IN;    // Write operation with a delay of 1 time unit
			
		end
		
	end
	
endmodule

group13_lab5_part2/reg_file_tb.v
//group 13

`include "regfile.v"

module reg_file_tb;
    
    reg [7:0] WRITEDATA;
    reg [2:0] WRITEREG, READREG1, READREG2;
    reg CLK, RESET, WRITEENABLE; 
    wire [7:0] REGOUT1, REGOUT2;
    
    regfile myregfile(WRITEDATA, WRITEREG,READREG1, READREG2,CLK,RESET, WRITEENABLE,REGOUT1, REGOUT2  );
       
    initial
    begin
        CLK = 1'b1;
        
        // generate files needed to plot the waveform using GTKWave
        $dumpfile("reg_file_wavedata.vcd");
		$dumpvars(0, reg_file_tb);
        
        // assign values with time to input signals to see output 
        RESET = 1'b0;
        WRITEENABLE = 1'b0;
        
        #4
        RESET = 1'b1;
        READREG1 = 3'd0;
        READREG2 = 3'd4;
        
        #6
        RESET = 1'b0;
        
        #2
        WRITEREG = 3'd2;
        WRITEDATA = 8'd95;
        WRITEENABLE = 1'b1;
        
        #7
        WRITEENABLE = 1'b0;
        
        #1
        READREG1 = 3'd2;
        
        #7
        WRITEREG = 3'd1;
        WRITEDATA = 8'd28;
        WRITEENABLE = 1'b1;
        READREG1 = 3'd1;
        
        #8
        WRITEENABLE = 1'b0;
        
        #8
        WRITEREG = 3'd4;
        WRITEDATA = 8'd6;
        WRITEENABLE = 1'b1;
        
        #8
        WRITEDATA = 8'd15;
        WRITEENABLE = 1'b1;
        
        #10
        WRITEENABLE = 1'b0;
        
        #6
        WRITEREG = -3'd1;
        WRITEDATA = 8'd50;
        WRITEENABLE = 1'b1;
        
        #5
        WRITEENABLE = 1'b0;
        
        #10
        $finish;
    end
    
    // clock signal generation
    always
        #4 CLK = ~CLK;
        

endmodule

group13_lab5_part2/reg_file_wavedata.vcd
$date
	Tue May 28 12:25:07 2024
$end
$version
	Icarus Verilog
$end
$timescale
	1s
$end
$scope module reg_file_tb $end
$var wire 8 ! REGOUT2 [7:0] $end
$var wire 8 " REGOUT1 [7:0] $end
$var reg 1 # CLK $end
$var reg 3 $ READREG1 [2:0] $end
$var reg 3 % READREG2 [2:0] $end
$var reg 1 & RESET $end
$var reg 8 ' WRITEDATA [7:0] $end
$var reg 1 ( WRITEENABLE $end
$var reg 3 ) WRITEREG [2:0] $end
$scope module myregfile $end
$var wire 1 # CLK $end
$var wire 8 * IN [7:0] $end
$var wire 3 + INADDRESS [2:0] $end
$var wire 3 , OUT1ADDRESS [2:0] $end
$var wire 3 - OUT2ADDRESS [2:0] $end
$var wire 8 . REGOUT1 [7:0] $end
$var wire 8 / REGOUT2 [7:0] $end
$var wire 1 & RESET $end
$var wire 1 ( WRITE $end
$var integer 32 0 i [31:0] $end
$upscope $end
$upscope $end
$enddefinitions $end
#0
$dumpvars
bx 0
bx /
bx .
bx -
bx ,
bx +
bx *
bx )
0(
bx '
0&
bx %
bx $
1#
bx "
bx !
$end
#4
0#
b100 %
b100 -
b0 $
b0 ,
1&
#8
1#
#9
b1000 0
#10
0&
#11
b0 !
b0 /
b0 "
b0 .
#12
1(
b1011111 '
b1011111 *
b10 )
b10 +
0#
#16
1#
#19
0(
#20
b10 $
b10 ,
0#
#22
b1011111 "
b1011111 .
#24
1#
#27
b1 $
b1 ,
1(
b11100 '
b11100 *
b1 )
b1 +
#28
0#
#29
b0 "
b0 .
#32
1#
#35
b11100 "
b11100 .
0(
#36
0#
#40
1#
#43
1(
b110 '
b110 *
b100 )
b100 +
#44
0#
#48
1#
#51
b110 !
b110 /
b1111 '
b1111 *
#52
0#
#56
1#
#59
b1111 !
b1111 /
#60
0#
#61
0(
#64
1#
#67
1(
b110010 '
b110010 *
b111 )
b111 +
#68
0#
#72
1#
0(
